func_kit/__init__.py
func_kit/cache.py
func_kit/cron.py
func_kit/log.py
func_kit-0.1.4.dist-info/WHEEL
func_kit-0.1.4.dist-info/LICENSE.txt
func_kit-0.1.4.dist-info/METADATA
func_kit-0.1.4.dist-info/RECORD
