Metadata-Version: 2.1
Name: func-kit
Version: 0.1.4
Summary: A set of useful function kits.
License: MIT
Author: ranguiquan
Author-email: ranguiquan@gmail.com
Requires-Python: >=3.9,<4.0
Classifier: License :: OSI Approved :: MIT License
Classifier: Programming Language :: Python :: 3
Classifier: Programming Language :: Python :: 3.9
Classifier: Programming Language :: Python :: 3.10
Classifier: Programming Language :: Python :: 3.11
Requires-Dist: croniter (>=1.3.14,<2.0.0)
